aioclaude_api.py
claude_api.py
aioclaude_api-1.0.15.dist-info/LICENSE
aioclaude_api-1.0.15.dist-info/METADATA
aioclaude_api-1.0.15.dist-info/WHEEL
aioclaude_api-1.0.15.dist-info/top_level.txt
aioclaude_api-1.0.15.dist-info/RECORD
