Metadata-Version: 2.1
Name: aioclaude-api
Version: 1.0.15
Summary: An unofficial API for Claude AI, allowing users to access and interact with Claude AII
Home-page: https://github.com/AmoreForever/Claude-API/
Author: Hikamoru
Author-email: me.thefarkhodov@gmail.com
License: MIT
Keywords: claude,ai,claude-ai,API,requests,chatbot,async,aiohttp
Classifier: Development Status :: 5 - Production/Stable
Classifier: Intended Audience :: Developers
Classifier: License :: OSI Approved :: MIT License
Classifier: Programming Language :: Python :: 3.7
Classifier: Programming Language :: Python :: 3
Classifier: Operating System :: Unix
Classifier: Operating System :: MacOS :: MacOS X
Classifier: Operating System :: Microsoft :: Windows
Requires-Python: >=3.8
License-File: LICENSE
Requires-Dist: aiohttp
Requires-Dist: requests
